setup.py
cml/__init__.py
cml.egg-info/PKG-INFO
cml.egg-info/SOURCES.txt
cml.egg-info/dependency_links.txt
cml.egg-info/requires.txt
cml.egg-info/top_level.txt