Metadata-Version: 1.0
Name: cml
Version: 0.0.1
Summary: just a simple test
Home-page: UNKNOWN
Author: yjw
Author-email: UNKNOWN
License: MIT License
Platform: any
